alita_session/__init__.py
alita_session/aioredis.py
alita_session/base.py
alita_session/fs.py
alita_session/mongo.py
alita_session/mysql.py
alita_session/redis.py
alita_session/utils.py
alita_session-0.1.4.dist-info/METADATA
alita_session-0.1.4.dist-info/RECORD
alita_session-0.1.4.dist-info/WHEEL
alita_session-0.1.4.dist-info/top_level.txt
