Metadata-Version: 2.1
Name: alita-session
Version: 0.1.4
Summary: alita-session is session extension for Alita。 
Home-page: https://github.com/dwpy/alita-session
Author: Dongwei
License: BSD
Project-URL: Documentation, https://github.com/dwpy/alita-session
Project-URL: Code, https://github.com/dwpy/alita-session
Platform: any
Classifier: Development Status :: 1 - Planning
Classifier: Environment :: Web Environment
Classifier: Intended Audience :: Developers
Classifier: License :: OSI Approved :: BSD License
Classifier: Operating System :: OS Independent
Classifier: Programming Language :: Python :: 3.5
Classifier: Programming Language :: Python :: 3.6
Classifier: Programming Language :: Python :: 3.7
Requires-Python: >=3.5
